setup.py
water/__init__.py
water/__main__.py
water.egg-info/PKG-INFO
water.egg-info/SOURCES.txt
water.egg-info/dependency_links.txt
water.egg-info/requires.txt
water.egg-info/top_level.txt